{
  "$schema": "https://schema.management.azure.com/schemas/2019-04-01/deploymentParameters.json#",
  "contentVersion": "1.0.0.0",
  "parameters": {
    "rgname": {
      "value": "rg-jmpcourt-dev01"
    },
    "vnetname": {
      "value": "vnet-jmpcourt-dev01"
    },
    "akvName": {
      "value": "akv-ade-ip"
    },
    "addressPrefix": {
      "value": "10.10.0.0/16"
    },
    "devcentername": {
      "value": "dc-jmpcourt-dev01"
    },
    "catalogName": {
      "value": "catalog"
    },
    "catalogRepoUri": {
      "value": "https://github.com/avl-sdv/DevOpsPilot.SiL.Workflows.git"
    },
    "catalogTasksName": {
      "value": "CustomizationTasksCatalog"
    },
    "catalogTasksRepoUri": {
      "value": "https://github.com/avl-sdv/DevOpsPilot.DevBox.CustomizationTasksCatalog.git"
    },
    "environmentName": {
      "value": "sandbox"
    },
    "law": {
      "value": "law-jmpcourt-dev01"
    },
    "location": {
      "value": "australiaeast"
    },
    "tags": {
      "value": {
        "infra": "customer",
        "env": "dev"
      }
    },
    "catalogRepoPat": {
      "value": "REPLACE_WITH_SECURE_PAT"
    },
    "privateDnsZoneName": {
      "value": "avl.lnk"
    },
    "subscriptionid": {
      "value": "250f62f2-46bc-4a3d-b362-d04ec87c9285"
    },
    "privateLinkServiceId": {
      "value": "/subscriptions/250f62f2-46bc-4a3d-b362-d04ec87c928/resourceGroups/rg-jmpcourt-dev01/providers/Microsoft.Network/privateLinkServices/pls-ade-ip"
    },
    "privateEndpointName": {
      "value": "pe-license-dev01"
    },
    "privateDnsRecordName": {
      "value": "license"
    }
  }
}